[
  {
    "id": "9995e139-5256-42e1-bfd4-5a46be0dc4d0",
    "billNumber": 1,
    "date": "2024-09-21 13:13:58",
    "returnedDate": "2024-09-30",
    "retirementDate": "2024-09-23",
    "returned": false,
    "amountTotal": 3000,
    "advancement": 0,
    "remainingBalance": 3000,
    "client": {
      "id": "d78f1323e-bbcc-42a2-9104-45bc97e98113",
      "name": "Alejo",
      "surname": "Araya",
      "dni": 42749595,
      "phoneNumber": 2613430975,
      "email": "alejoaraya2000@gmail.com",
      "direction": "Calle 7",
      "departament": "Ciudad",
      "postalCode": 5500,
      "blacklist": false,
      "dischargeDate": ""
    },
    "costumes": [
      {
        "id": "42bcc9f1-e008-461c-aba0-dd0828ed8a41",
        "name": "Bombero",
        "category": {
          "name": "Adulto",
          "price": 2500,
          "id": "9d6ec1d1-874d-4bdd-8cf7-0fc4b560c732",
          "dischargeDate": ""
        },
        "details": "asdasdas",
        "price": 2500,
        "dischargeDate": ""
      }
    ],
    "others": [
      {
        "name": "Vincha",
        "price": 500
      }
    ],
    "note": "Gracias",
    "dischargeDate": ""
  }
]